hockey_analytics/__init__.py
hockey_analytics/viz.py
hockey_analytics-2022.3292.dist-info/LICENSE
hockey_analytics-2022.3292.dist-info/WHEEL
hockey_analytics-2022.3292.dist-info/METADATA
hockey_analytics-2022.3292.dist-info/RECORD
