Metadata-Version: 2.1
Name: hockey_analytics
Version: 2022.3292
Summary: A python package to facilitate working with hockey data.
Author-email: Brock Tibert <btibert3@gmail.com>
Classifier: License :: OSI Approved :: MIT License
Project-URL: Home, https://github.com/Btibert3/hockey-analytics
